{
    "sections": [
        {
            "title": "Accueil",
            "href": "/"
        },
        {
            "title": "A propos",
            "href": "/about"
        },
        {
            "title": "Compétences",
            "href": "/skills"
        },
        {
            "title": "Formation",
            "href": "/education"
        },
        {
            "title": "Expérience",
            "href": "/experience"
        },
        {
            "title": "Projets",
            "href": "/projects"
        }
    ]

}